prettyc
