Metadata-Version: 2.1
Name: prettyc
Version: 1.0.4
Summary: Fork of Google's cpplint, modified to work only with C.
Home-page: http://github.com/pylover/prettyc
Author: Vahid Mardani
Author-email: vahid.mardani@gmail.com
License: BSD-3-Clause
Keywords: lint,python,c
Platform: UNKNOWN
Classifier: Programming Language :: Python
Classifier: Programming Language :: Python :: 3
Classifier: Programming Language :: Python :: 3.6
Classifier: Programming Language :: Python :: 3.7
Classifier: Programming Language :: Python :: 3.8
Classifier: Programming Language :: Python :: 3.9
Classifier: Programming Language :: Python :: 3.10
Classifier: Programming Language :: C
Classifier: Development Status :: 5 - Production/Stable
Classifier: Environment :: Console
Classifier: Topic :: Software Development :: Quality Assurance
Classifier: License :: OSI Approved :: BSD License
License-File: LICENSE
